MANIFEST.in
README.rst
setup.py
Showtime/__init__.py
Showtime/zst_base.py
Showtime/zst_mailman.py
Showtime/zst_method.py
Showtime/zst_node.py
Showtime/zst_peerLink.py
Showtime/zst_socket.py
Showtime/zst_stage.py
Showtime_Python.egg-info/PKG-INFO
Showtime_Python.egg-info/SOURCES.txt
Showtime_Python.egg-info/dependency_links.txt
Showtime_Python.egg-info/requires.txt
Showtime_Python.egg-info/top_level.txt
examples/__init__.py
examples/example_SinewaveNode.py
scripts/st-methodeditor.py
scripts/st-methodsubscriber.py
scripts/st-sinewriter.py
scripts/st-stage.py