Metadata-Version: 1.1
Name: Showtime-Python
Version: 1.0.6
Summary: Showtime-Python allows you to connect multiple programs for live performances using nodes.
Home-page: http://github.com/Mystfit/Showtime
Author: Byron Mallett
Author-email: byronated@gmail.com
License: MIT
Platform: UNKNOWN
Classifier: Development Status :: 4 - Beta
Classifier: License :: OSI Approved :: MIT License
Classifier: Operating System :: Microsoft :: Windows :: Windows 7
Classifier: Operating System :: MacOS :: MacOS X
Classifier: Operating System :: OS Independent
Classifier: Environment :: Console
Classifier: Programming Language :: Python
Classifier: Programming Language :: Python :: 2.7
Classifier: Programming Language :: Python :: 3.3
Classifier: Programming Language :: C#
Classifier: Programming Language :: Java
Classifier: Topic :: Software Development :: Libraries :: Python Modules
Classifier: Topic :: Software Development :: Object Brokering
Classifier: Intended Audience :: Developers
Classifier: Natural Language :: English
